pyicloud_ipd/__init__.py
pyicloud_ipd/base.py
pyicloud_ipd/cmdline.py
pyicloud_ipd/exceptions.py
pyicloud_ipd/utils.py
pyicloud_ipd/services/__init__.py
pyicloud_ipd/services/account.py
pyicloud_ipd/services/calendar.py
pyicloud_ipd/services/contacts.py
pyicloud_ipd/services/findmyiphone.py
pyicloud_ipd/services/photos.py
pyicloud_ipd/services/reminders.py
pyicloud_ipd/services/ubiquity.py
pyicloud_ipd/tests/__init__.py
pyicloud_ipd/tests/test_sanity.py
pyicloud_ipd-0.10.1.dist-info/LICENSE.txt
pyicloud_ipd-0.10.1.dist-info/METADATA
pyicloud_ipd-0.10.1.dist-info/WHEEL
pyicloud_ipd-0.10.1.dist-info/entry_points.txt
pyicloud_ipd-0.10.1.dist-info/top_level.txt
pyicloud_ipd-0.10.1.dist-info/RECORD
