Metadata-Version: 2.1
Name: pyicloud-ipd
Version: 0.10.1
Summary: PyiCloud is a module which allows pythonistas to interact with iCloud webservices.
Home-page: https://github.com/ndbroadbent/pyicloud
Maintainer: The PyiCloud Authors
Maintainer-email: 
License: MIT
Platform: UNKNOWN
Classifier: Intended Audience :: Developers
Classifier: Operating System :: OS Independent
Classifier: Programming Language :: Python
Classifier: Programming Language :: Python :: 2.6
Classifier: Programming Language :: Python :: 2.7
Classifier: Programming Language :: Python :: 3
Classifier: License :: OSI Approved :: MIT License
Requires-Dist: requests (>=1.2)
Requires-Dist: keyring (<9.0,>=8.0)
Requires-Dist: keyrings.alt (<2.0,>=1.0)
Requires-Dist: click (<7.0,>=6.0)
Requires-Dist: six (>=1.9.0)
Requires-Dist: tzlocal
Requires-Dist: pytz
Requires-Dist: certifi
Requires-Dist: future
